Workbook

Sheet README
A1: ESG Momentum Radar — Cost & Scale Model (CALCULATING VERSION)
A2: Built by scripts/build_cost_workbook.py. Re-run it to refresh; do not hand-edit, the inputs live in files.
A4: COLOUR CONVENTION
A5: BLUE = an input you can change. Every input row carries its Source.
A6: BLACK = a formula. Excel computes it. Overwriting one breaks the model.
A7: AMBER + shaded = still needed. Left EMPTY on purpose — a plausible number in a cost model is worse than a blank one, because a blank gets asked about.
A9: WHAT CHANGED FROM THE SKELETON
A10: The skeleton assumed 40 signals/company/month at 1,500 tokens/signal. That describes a system where a model does the scoring. This one does not: scoring is rule-based and costs ZERO tokens. All LLM cost is in GATHERING evidence, charged per SWEEP of a company, not per signal. The Unit Economics tab is built on the measured figure.
A12: THE TWO MONEY STORIES — never mix them
A13: PILOT ASK (commercial): what the pilot costs at real market rates. Pilot Cost tab.
A14: HACKATHON ACTUALS: what the team is really spending this semester. Separate tab.
A16: SOURCES BEHIND THE FILLED CELLS
... A19: LLM prices: supplied at build time from the provider's published card. This model never guesses a price.

Sheet Assumptions
A1: ASSUMPTIONS — the only tab you edit
A2: Blue = input. Amber + shaded = still needed, deliberately left empty.
A4: Assumption | B4: Value | C4: Unit | D4: Source / note
A5: PEOPLE — pilot team
A6: Data / ML engineer — day rate | B6: 405 | C6: SGD/day | D6: MyCareersFuture: median of 60 postings (335 matched), S$7,500/mo x 12 x 1.17 / 260
A7: Full-stack engineer — day rate | B7: 398 | C7: SGD/day | D7: MyCareersFuture: median of 60 postings (114 matched), S$7,375/mo x 12 x 1.17 / 260
A8: Domain / ESG analyst — day rate | B8: 290 | C8: SGD/day | D8: MyCareersFuture: median of 60 postings (143 matched), S$5,375/mo x 12 x 1.17 / 260 !! WIDE SAMPLE, LOW MEDIAN. 'ESG' matches any posting mentioning it, including junior operations roles, which pulls the median down. Narrower terms return far higher rates on samples
A9: Project manager — day rate | B9: 435 | C9: SGD/day | D9: MyCareersFuture: median of 60 postings (3450 matched), S$8,050/mo x 12 x 1.17 / 260
A10: Pilot duration | B10: 6 | C10: weeks | D10: Buyer journey — pilot stage is 6 weeks
A11: Working days per week | B11: 5 | C11: days | D11: Standard
A12: Data/ML engineer — FTE | B12: 1 | C12: FTE | D12: Team plan
A13: Full-stack — FTE | B13: 1 | C13: FTE | D13: Team plan
A14: Domain analyst — FTE | B14: 0.5 | C14: FTE | D14: Team plan
A15: PM — FTE | B15: 0.5 | C15: FTE | D15: Team plan
A16: DATA & LICENSING
A17: LSEG / baseline ESG feed — pilot | C17: SGD total | D17: NEEDS QUOTE — enquiry to LSEG/CGSI, no reply. If none, model from comparables and SAY SO on the slide.
A18: Licensed job-posting feed | C18: SGD total | D18: NEEDS QUOTE — licensed feeds only, no scraping.
A19: Exchange filings (SGX/Bursa/IDX/SET/PSE) | B19: 0 | C19: SGD total | D19: Free — public portals
A20: Patent data (EPO OPS free tier) | B20: 0 | C20: SGD total | D20: Free tier
A21: Industry benchmark (Eurostat) | B21: 0 | C21: SGD total | D21: Free, keyless — env_ac_aeint_r2. All 22 rows reproduce live.
A22: INFRASTRUCTURE & INFERENCE
A23: Cloud hosting & storage — pilot | B23: 2000 | C23: SGD total | D23: Slide 16 figure. Cross-check vs the ~S$52/semester Alibaba actual.
A24: Prompt tokens per company per SWEEP | B24: 5604 | C24: tokens | D24: MEASURED over 28 companies (harvest.py --cost)
A25: Output tokens per company per SWEEP | B25: 455 | C25: tokens | D25: MEASURED — never discounted by the cache
A26: Cacheable prompt share | B26: 0.288 | C26: share | D26: MEASURED — the byte-identical system prompt, 28.8% of the prompt
A27: Cache hit rate on the cacheable share | B27: 0.9 | C27: share | D27: Assumption. Applies ONLY to the cacheable share, never to output.
A28: Sweeps per company per month | B28: 4 | C28: sweeps | D28: Cadence decision — 4 = weekly
A29: Tokens per signal (SCORING path) | B29: 0 | C29: tokens | D29: MEASURED — structurally zero. signals.py routes by rule, engine.py scores deterministically; no LLM is reachable from either.
A30: Price — 1M input, cache HIT | B30: 0.007 | C30: USD | D30: Provider published card. SUPPLIED at build time; never guessed.
A31: Price — 1M input, cache MISS | B31: 0.22 | C31: USD | D31: Provider published card
A32: Price — 1M output | B32: 0.66 | C32: USD | D32: Provider published card
A33: USD:SGD | B33: 1.35 | C33: rate | D33: Set to the rate used on the slide
A34: COVERAGE
A35: Companies covered — pilot | B35: 52 | C35: companies | D35: The CGSI verified basket
A36: Companies covered — Year 1 | B36: 500 | C36: companies | D36: Scenario lever
A37: Companies covered — Year 3 | B37: 2000 | C37: companies | D37: Scenario lever

Sheet Pilot Cost
A1: PILOT COST — bottom-up, commercial rates
A2: Calculates from Assumptions. Amber rows are blank until a quote arrives.
A4: Line | B4: SGD | C4: Basis
A5: PEOPLE
A6: Data / ML engineer | B6: =Assumptions!$B$6*Assumptions!$B$10*Assumptions!$B$11*Assumptions!$B$12 | C6: day rate x weeks x days/week x FTE
A7: Full-stack engineer | B7: =Assumptions!$B$7*Assumptions!$B$10*Assumptions!$B$11*Assumptions!$B$13 | C7: day rate x weeks x days/week x FTE
A8: Domain / ESG analyst | B8: =Assumptions!$B$8*Assumptions!$B$10*Assumptions!$B$11*Assumptions!$B$14 | C8: day rate x weeks x days/week x FTE
A9: Project manager | B9: =Assumptions!$B$9*Assumptions!$B$10*Assumptions!$B$11*Assumptions!$B$15 | C9: day rate x weeks x days/week x FTE
A10: People subtotal | B10: =SUM(B6:B9)
A12: DATA & LICENSING
A13: LSEG / baseline ESG feed | B13: =Assumptions!$B$17 | C13: from Assumptions — BLANK until a quote arrives
A14: Licensed job-posting feed | B14: =Assumptions!$B$18 | C14: from Assumptions — BLANK until a quote arrives
A15: Free sources (filings, patents, Eurostat) | B15: 0 | C15: free by design
A16: Data subtotal | B16: =SUM(B13:B15)
A18: INFRASTRUCTURE & INFERENCE
A19: Cloud hosting & storage | B19: =Assumptions!$B$23 | C19: from Assumptions
A20: LLM inference — pilot window | B20: =Assumptions!$B$35*'Unit Economics'!$B$9*Assumptions!$B$28*1.5 | C20: companies x SGD per company per sweep x sweeps/month x 1.5 months (the 6-week pilot)
A21: Infrastructure subtotal | B21: =SUM(B19:B20)
A23: COMPLIANCE & OTHER
A24: Legal review | C24: NEEDS A QUOTE
A25: Professional indemnity insurance | C25: NEEDS A QUOTE
A26: Compliance subtotal | B26: =SUM(B24:B25)
A28: TOTAL — fully loaded pilot | B28: =B10+B16+B21+B26 | C28: INCOMPLETE while the amber rows are blank. Say so on the slide rather than presenting this as the fully-loaded number.

Sheet Unit Economics
A1: UNIT ECONOMICS — cost to cover one company
A2: Inference only. Excludes the fixed data licence — that is the cost which falls per company as clients are added.
A4: Metric | B4: Value | C4: Basis
A5: Prompt tokens billed at HIT price | B5: =Assumptions!$B$24*Assumptions!$B$26*Assumptions!$B$27 | C5: prompt x cacheable share x hit rate
A6: Prompt tokens billed at MISS price | B6: =Assumptions!$B$24-B5 | C6: everything in the prompt the cache did not serve
A7: Output tokens per sweep | B7: =Assumptions!$B$25 | C7: MEASURED — never discounted by the cache
A8: USD per company per sweep | B8: =(B5/1000000*Assumptions!$B$30)+(B6/1000000*Assumptions!$B$31)+(B7/1000000*Assumptions!$B$32) | C8: a cache HIT is a cheaper RATE, not free — priced separately, never written off
A9: SGD per company per sweep | B9: =B8*Assumptions!$B$33 | C9: USD x FX
A10: SGD per company per MONTH | B10: =B9*Assumptions!$B$28 | C10: x sweeps per month
A11: SGD per company per YEAR | B11: =B10*12 | C11: x 12
A13: The data licence is a FIXED cost shared across all clients. Inference is the only truly variable cost, and it is linear in companies.
A14: So the marginal-cost-per-company line is FLAT on inference alone. It falls only once the fixed licence is spread across clients — which cannot be charted until a quote exists. Drawing a falling line before then is drawing the conclusion first.

Sheet Scale Scenarios
A1: SCALE SCENARIOS — annual run-rate
A2: Annual run-rate, including the Pilot column. The Pilot Cost tab is a 6-week spend — a different basis. Do not compare totals.
A4: Metric | B4: Pilot | C4: Year 1 | D4: Year 3 | E4: Basis
A5: Companies covered | B5: =Assumptions!$B$35 | C5: =Assumptions!$B$36 | D5: =Assumptions!$B$37 | E5: from Assumptions
A6: Inference (SGD/yr) | B6: =B5*'Unit Economics'!$B$11 | C6: =C5*'Unit Economics'!$B$11 | D6: =D5*'Unit Economics'!$B$11 | E6: companies x SGD per company per year
A7: People (SGD/yr) | E7: NEEDS headcount plan + licence quote
A8: Data & licensing (SGD/yr) | E8: NEEDS headcount plan + licence quote
A9: Cloud & infra (SGD/yr) | E9: NEEDS headcount plan + licence quote
A10: Total cost (SGD/yr) | B10: =SUM(B6:B9) | C10: =SUM(C6:C9) | D10: =SUM(D6:D9)
A12: Marginal cost per company — INFERENCE ONLY | B12: ='Unit Economics'!$B$11 | C12: ='Unit Economics'!$B$11 | D12: ='Unit Economics'!$B$11 | E12: FLAT by construction — inference is linear in companies. This is NOT the falling chart; that needs the fixed licence spread across clients.
A13: Total cost per company (SGD/yr) | B13: =B10/B5 | C13: =C10/C5 | D13: =D10/D5 | E13: THIS is the line that falls — once People and Data are filled.

Sheet Hackathon Actuals
A1: HACKATHON ACTUALS — what the team is really spending
A2: Never mix with the commercial pilot ask. Label both wherever they appear.
A4: Line | B4: SGD | C4: Source
A5: Alibaba Cloud hosting (2 vCPU / 2GB), semester | B5: 52 | C5: Methodology Appendix A
A6: Bandwidth / storage buffer | B6: 13 | C6: Methodology Appendix A
A7: DeepSeek credits — dev + demo | B7: 19 | C7: Methodology Appendix A
A8: Public demo domain + SSL (one-time) | B8: 19 | C8: Methodology Appendix A
A9: Testnet anchoring gas | B9: 0 | C9: Testnet — effectively zero
A10: Subtotal | B10: =SUM(B5:B9)
A11: Contingency @ 15% | B11: =B10*0.15
A12: TOTAL — hackathon actuals | B12: =B10+B11

Sheet Pricing & Ask
A1: PRICING & THE FUNDING ASK
A2: Two cells here are business DECISIONS, not lookups. They stay blank until somebody decides.
A4: Metric | B4: Year 1 | C4: Year 3 | D4: Note
A5: Annual price per firm (SGD) | D5: NEEDS A NUMBER — anchor to a public ESG subscription comparable and cite it.
A6: Customers | D6: NEEDS A PLAN
A7: Revenue | B7: =B5*B6 | C7: =C5*C6
A8: Total cost | B8: ='Scale Scenarios'!C10 | C8: ='Scale Scenarios'!D10
A9: Margin | B9: =B7-B8 | C9: =C7-C8
A11: THE ASK
A12: Amount requested (SGD) | B12: ='Pilot Cost'!B28 | D12: Defaults to the fully-loaded pilot — which is INCOMPLETE until the amber rows fill
A13: Months it funds | B13: 6 | D13: Pilot duration
A14: Milestone it buys | D14: NEEDS A SPECIFIC, CHECKABLE MILESTONE — not 'build the product'
